Metadata-Version: 2.4
Name: mini-pentest-scanner
Version: 1.0.0
Summary: Non-intrusive Security Assessment Tool - Educational Security Scanner
Home-page: https://github.com/yourname/mini-pentest-lab
Author: Mini Pentest Lab
Author-email: Mini Pentest Lab <info@example.com>
License: MIT
Project-URL: Homepage, https://github.com/yourname/mini-pentest-lab
Project-URL: Documentation, https://github.com/yourname/mini-pentest-lab/docs
Project-URL: Repository, https://github.com/yourname/mini-pentest-lab
Keywords: security,scanner,pentest,vulnerability,assessment
Classifier: Development Status :: 4 - Beta
Classifier: Intended Audience :: Education
Classifier: Intended Audience :: Information Technology
Classifier: License :: OSI Approved :: MIT License
Classifier: Programming Language :: Python :: 3
Classifier: Programming Language :: Python :: 3.9
Classifier: Programming Language :: Python :: 3.10
Classifier: Programming Language :: Python :: 3.11
Classifier: Topic :: Security
Classifier: Topic :: Education
Requires-Python: >=3.9
License-File: LICENSE
Requires-Dist: requests>=2.31.0
Requires-Dist: PyYAML>=6.0.1
Requires-Dist: reportlab>=4.0.0
Provides-Extra: dev
Requires-Dist: pytest>=7.0.0; extra == "dev"
Requires-Dist: black>=23.0.0; extra == "dev"
Requires-Dist: flake8>=6.0.0; extra == "dev"
Dynamic: author
Dynamic: home-page
Dynamic: license-file
Dynamic: requires-python
